odoo10_addon_account_invoice_production_lot-10.0.1.1.0-py2.7-nspkg.pth
odoo/addons/account_invoice_production_lot/README.rst
odoo/addons/account_invoice_production_lot/__init__.py
odoo/addons/account_invoice_production_lot/__manifest__.py
odoo/addons/account_invoice_production_lot/demo/sale.xml
odoo/addons/account_invoice_production_lot/i18n/es.po
odoo/addons/account_invoice_production_lot/models/__init__.py
odoo/addons/account_invoice_production_lot/models/account_invoice.py
odoo/addons/account_invoice_production_lot/report/report_invoice.xml
odoo/addons/account_invoice_production_lot/tests/__init__.py
odoo/addons/account_invoice_production_lot/tests/test_invoice_production_lot.py
odoo/addons/account_invoice_production_lot/views/account_invoice_views.xml
odoo10_addon_account_invoice_production_lot-10.0.1.1.0.dist-info/DESCRIPTION.rst
odoo10_addon_account_invoice_production_lot-10.0.1.1.0.dist-info/METADATA
odoo10_addon_account_invoice_production_lot-10.0.1.1.0.dist-info/RECORD
odoo10_addon_account_invoice_production_lot-10.0.1.1.0.dist-info/WHEEL
odoo10_addon_account_invoice_production_lot-10.0.1.1.0.dist-info/metadata.json
odoo10_addon_account_invoice_production_lot-10.0.1.1.0.dist-info/namespace_packages.txt
odoo10_addon_account_invoice_production_lot-10.0.1.1.0.dist-info/top_level.txt
